atelier_formation/__init__.py
atelier_formation-0.1.dist-info/METADATA
atelier_formation-0.1.dist-info/WHEEL
atelier_formation-0.1.dist-info/top_level.txt
atelier_formation-0.1.dist-info/RECORD
